M_E_GA/GA_Logger.py
M_E_GA/M_E_Engine.py
M_E_GA/M_E_GA_Base.py
M_E_GA/__init__.py
M_E_GA/engine/__init__.py
M_E_GA/engine/crossover_manager.py
M_E_GA/engine/gene_manager.py
M_E_GA/engine/logging_manager.py
M_E_GA/engine/meta_gene_manager.py
M_E_GA/engine/mutation_manager.py
M_E_GA/engine/organism_generator.py
M_E_GA/engine/population_manager.py
M_E_GA/engine/mutation/__init__.py
M_E_GA/engine/mutation/basic_mutations.py
M_E_GA/engine/mutation/delimiter_mutations.py
M_E_GA/engine/mutation/metagene_mutations.py
m_e_ga2-2.0.0b6.dist-info/LICENSE.txt
m_e_ga2-2.0.0b6.dist-info/METADATA
m_e_ga2-2.0.0b6.dist-info/WHEEL
m_e_ga2-2.0.0b6.dist-info/top_level.txt
m_e_ga2-2.0.0b6.dist-info/RECORD
